hdltobq/hdltobq.py
hdltobq-0.0.1.dist-info/METADATA
hdltobq-0.0.1.dist-info/WHEEL
hdltobq-0.0.1.dist-info/top_level.txt
hdltobq-0.0.1.dist-info/RECORD
